Workbook

Sheet HOW TO USE
B3: USER INSTRUCTIONS
B5: > Save this spreadsheet to your computer.
B7: >> On the "LOSS LIST" sheet, complete as much detail in the white boxes as you can, saving regularly (just in case).
B9: >>> Once completed, double checked and saved, kindly email it back to us at . . . claims@davies-group.com
B10: Please include your claims reference number and Post Code in the email heading.
B12: Thank You for your time and effort in compiling this list, it helps us to help you.
B16: SUPPORTING YOUR OWNERSHIP
B18: Please collate and retain safely as many of the various forms of ownership as possible (as described in column F of the Loss List sheet), as your Insurer may wish to view these at any time.

Sheet LOSS LIST
C1: YOUR NAME : | I1: TOTAL | J1: TOTAL
C2: CLAIM REF NUMBER :
C3: NAME OF YOUR INSURER :
B4: ITEM DESCRIPTION | C4: HOW OLD IS IT? | D4: WHERE & WHEN PURCHASED? | E4: 1. BY WHOM? 2. METHOD OF PAYMENT? | F4: WHO DOES THE ITEM BELONG TO? | G4: WHERE WAS THE ITEM (GARDEN? IN SHED?) | H4: I CAN PROVIDE 1. Purchase receipt / invoice. 2. Valuation (Jewellers). 3. Original Box / Packaging. 4. Instruction Manual. 5. Remote Control. 6. Photo(s) where item appears. | I4: £ ORIGINAL PURCHASE PRICE/COST | J4: £ COST TO BUY TODAY (Amount Claimed) | K4: NOTES / COMMENTS / INTERNET LINKS
A5: 1
A6: 2
A7: 3
A8: 4
A9: 5
A10: 6
A11: 7
A12: 8
A13: 9
A14: 10
A15: 11
A16: 12
... A234: 230

Sheet Office Use - Settlement
K2: Ctns SI | M2: 0
K3: HR Limit | L3: 0 | M3: 0
K4: HR SAL | L4: 0 | M4: 0
B5: Settlement for: | K5: Unspec PP | L5: 0 | M5: 0
B6: =IF('LOSS LIST'!G1 =0, "- -",'LOSS LIST'!G1) -> - - | E6: SUPPLIER VALIDATED | H6: Method x | K6: Unspec PP SAL | L6: 0 | M6: 0
B7: =IF('LOSS LIST'!G2 =0, "- -",'LOSS LIST'!G2) -> - -
B8: ITEM | C8: AMOUNT CLAIMED BY PH | E8: Suppliers Name | F8: Gross Validated Cost | G8: Discounted Validated Cost | H8: Cash | I8: Replaced | K8: W&T Deduction Amount | M8: ACTUAL SETTLED | O8: NOTES
C9: =SUM(C10:C239) -> 0 | F9: =SUM(F10:F239) -> 0 | G9: =SUM(G10:G239) -> 0 | K9: =SUM(K10:K239) -> 0 | M9: =SUM(M10:M239) -> 0
A10: 1 | B10: =IF('LOSS LIST'!B5 = 0, "-", 'LOSS LIST'!B5) -> - | C10: =IF('LOSS LIST'!J5 = 0, "-", 'LOSS LIST'!J5) -> -
A11: 2 | B11: =IF('LOSS LIST'!B6 = 0, "-", 'LOSS LIST'!B6) -> - | C11: =IF('LOSS LIST'!J6 = 0, "-", 'LOSS LIST'!J6) -> -
A12: 3 | B12: =IF('LOSS LIST'!B7 = 0, "-", 'LOSS LIST'!B7) -> - | C12: =IF('LOSS LIST'!J7 = 0, "-", 'LOSS LIST'!J7) -> -
A13: 4 | B13: =IF('LOSS LIST'!B8 = 0, "-", 'LOSS LIST'!B8) -> - | C13: =IF('LOSS LIST'!J8 = 0, "-", 'LOSS LIST'!J8) -> -
A14: 5 | B14: =IF('LOSS LIST'!B9 = 0, "-", 'LOSS LIST'!B9) -> - | C14: =IF('LOSS LIST'!J9 = 0, "-", 'LOSS LIST'!J9) -> -
A15: 6 | B15: =IF('LOSS LIST'!B10 = 0, "-", 'LOSS LIST'!B10) -> - | C15: =IF('LOSS LIST'!J10 = 0, "-", 'LOSS LIST'!J10) -> -
A16: 7 | B16: =IF('LOSS LIST'!B11 = 0, "-", 'LOSS LIST'!B11) -> - | C16: =IF('LOSS LIST'!J11 = 0, "-", 'LOSS LIST'!J11) -> -
A17: 8 | B17: =IF('LOSS LIST'!B12 = 0, "-", 'LOSS LIST'!B12) -> - | C17: =IF('LOSS LIST'!J12 = 0, "-", 'LOSS LIST'!J12) -> -
A18: 9 | B18: =IF('LOSS LIST'!B13 = 0, "-", 'LOSS LIST'!B13) -> - | C18: =IF('LOSS LIST'!J13 = 0, "-", 'LOSS LIST'!J13) -> -
A19: 10 | B19: =IF('LOSS LIST'!B14 = 0, "-", 'LOSS LIST'!B14) -> - | C19: =IF('LOSS LIST'!J14 = 0, "-", 'LOSS LIST'!J14) -> -
A20: 11 | B20: =IF('LOSS LIST'!B15 = 0, "-", 'LOSS LIST'!B15) -> - | C20: =IF('LOSS LIST'!J15 = 0, "-", 'LOSS LIST'!J15) -> -
A21: 12 | B21: =IF('LOSS LIST'!B16 = 0, "-", 'LOSS LIST'!B16) -> - | C21: =IF('LOSS LIST'!J16 = 0, "-", 'LOSS LIST'!J16) -> -
... A239: 230 | B239: =IF('LOSS LIST'!B234 = 0, "-", 'LOSS LIST'!B234) -> - | C239: =IF('LOSS LIST'!J234 = 0, "-", 'LOSS LIST'!J234) -> -
C240: =SUM(C10:C239) -> 0 | E240: =SUM(E11:E239) -> 0 | G240: =SUM(G11:G239) -> 0 | K240: =SUM(K11:K239) -> 0 | M240: =SUM(M11:M239) -> 0
